openpy_dsse/__init__.py
openpy_dsse/Algorithm_classification.py
openpy_dsse/base_DSSE.py
openpy_dsse/COM_interface.py
openpy_dsse/DSSE_algorithms/__init__.py
openpy_dsse/DSSE_algorithms/Symb_Eqn/__init__.py
openpy_dsse/DSSE_algorithms/Symb_Eqn/sym_func_1ph.py
openpy_dsse/DSSE_algorithms/Symb_Eqn/sym_func_Pos_Seq.py
openpy_dsse/DSSE_algorithms/WLS_alg_1ph.py
openpy_dsse/DSSE_algorithms/WLS_alg_Pos_Seq.py
openpy_dsse/Elec_param_calc_DSS_EST.py
openpy_dsse/error_handling_logging.py
openpy_dsse/examples/13NodeIEEE/MEAS_files/Init_Bus_i.json
openpy_dsse/examples/13NodeIEEE/MEAS_files/Init_Bus_i_PMU.json
openpy_dsse/examples/13NodeIEEE/MEAS_files/Init_Elem_ft.json
openpy_dsse/examples/13NodeIEEE/MEAS_files/Init_Elem_ft_PMU.json
openpy_dsse/examples/13NodeIEEE/MEAS_files/MEAS_Bus_i.json
openpy_dsse/examples/13NodeIEEE/MEAS_files/MEAS_Bus_i_PMU.json
openpy_dsse/examples/13NodeIEEE/MEAS_files/MEAS_Elem_ft.json
openpy_dsse/examples/13NodeIEEE/MEAS_files/MEAS_Elem_ft_PMU.json
openpy_dsse/examples/13NodeIEEE/MEAS_files/Pos_MEAS_Bus_i.json
openpy_dsse/examples/13NodeIEEE/MEAS_files/Pos_MEAS_Bus_i_PMU.json
openpy_dsse/examples/13NodeIEEE/MEAS_files/Pos_MEAS_Elem_ft.json
openpy_dsse/examples/13NodeIEEE/MEAS_files/Pos_MEAS_Elem_ft_PMU.json
openpy_dsse/examples/13NodeIEEE/OpenDSS files/Capacitors.DSS
openpy_dsse/examples/13NodeIEEE/OpenDSS files/DSSViewIntercom.Txt
openpy_dsse/examples/13NodeIEEE/OpenDSS files/IEEE13Node_BusXY.csv
openpy_dsse/examples/13NodeIEEE/OpenDSS files/IEEE13Nodeckt_Power.dbl
openpy_dsse/examples/13NodeIEEE/OpenDSS files/IEEE13Nodeckt_Power.DSV
openpy_dsse/examples/13NodeIEEE/OpenDSS files/IEEELineCodes.DSS
openpy_dsse/examples/13NodeIEEE/OpenDSS files/LineCodes.dss
openpy_dsse/examples/13NodeIEEE/OpenDSS files/Lines.DSS
openpy_dsse/examples/13NodeIEEE/OpenDSS files/Loads.DSS
openpy_dsse/examples/13NodeIEEE/OpenDSS files/Master13NodeIEEE.dss
openpy_dsse/examples/13NodeIEEE/OpenDSS files/PosSeq circuit/BusCoords.dss
openpy_dsse-0.1.4.dist-info/LICENSE.md
openpy_dsse-0.1.4.dist-info/METADATA
openpy_dsse-0.1.4.dist-info/WHEEL
openpy_dsse-0.1.4.dist-info/RECORD
