Metadata-Version: 2.1
Name: openpy-dsse
Version: 0.1.4
Summary: Open source library for state estimation of a distribution network modeled in OpenDSS
License: LICENSE
Keywords: OpenDSS,DSSE,state estimation,smart grid,OpenPy-DSSE,OpenPy_DSSE
Author: Jorge Lara
Author-email: jlara@iee.unsj.edu.ar
Requires-Python: >=3.8,<4.0
Classifier: License :: Other/Proprietary License
Classifier: Programming Language :: Python :: 3
Classifier: Programming Language :: Python :: 3.8
Classifier: Programming Language :: Python :: 3.9
Classifier: Programming Language :: Python :: 3.10
Classifier: Programming Language :: Python :: 3.11
Requires-Dist: colorama (==0.4.6)
Requires-Dist: contourpy (==1.0.5)
Requires-Dist: cycler (==0.11.0)
Requires-Dist: et-xmlfile (==1.1.0)
Requires-Dist: fonttools (==4.38.0)
Requires-Dist: kiwisolver (==1.4.4)
Requires-Dist: matplotlib (==3.6.0)
Requires-Dist: mpmath (==1.2.1)
Requires-Dist: numpy (==1.23.5)
Requires-Dist: openpyxl (==3.0.10)
Requires-Dist: packaging (==21.3)
Requires-Dist: pandas (==1.2.3)
Requires-Dist: pillow (==9.2.0)
Requires-Dist: py-dss-interface (==1.0.2)
Requires-Dist: pyparsing (==3.0.9)
Requires-Dist: python-dateutil (==2.8.2)
Requires-Dist: pytz (==2022.6)
Requires-Dist: scipy (==1.9.3)
Requires-Dist: seaborn (==0.12.1)
Requires-Dist: six (==1.16.0)
Requires-Dist: sympy (==1.11.1)
